Workbook
Name anos: 'planilha 1'!$C$15
Name aporte: 'planilha 1'!$C$14
Name perfil_selecionado: 'planilha 1'!$C$17
Name salario: 'planilha 1'!$C$12
Name taxa_mensal: 'planilha 1'!$C$16

Sheet planilha 1
B11: 1. CONFIGURAÇÕES E ENTRADAS DE DADOS | F11: 2. RESUMO DE RESULTADOS
B12: Salário Mensal (R$) | C12: 5000 | F12: 1. Quanto investir por mês? | G12: =aporte -> 1500
B13: Sugestão de Aporte (30%) | C13: =C12*0.3 -> 1500 | F13: 2. Por quantos anos? | G13: =anos & " anos" -> 10 anos
B14: Aporte Mensal Desejado (R$) | C14: 1500 | F14: 3. Qual a taxa mensal? | G14: =taxa_mensal -> 0.008
B15: Período de Investimento (Anos) | C15: 10 | F15: 4. Patrimônio Acumulado (VF): | G15: =FV(taxa_mensal, anos*12, -aporte) -> 300326.2
B16: Taxa Mensal Estimada (%) | C16: 0.008 | F16: 5. Dividendos Mensais Estimados: | G16: =G15*taxa_mensal -> 2402.6096
B17: Perfil de Investidor | C17: Moderado
B20: 3. PROJEÇÃO DE CENÁRIOS TEMPORAIS | F20: 4. ALOCAÇÃO DO APORTE POR PERFIL DE INVESTIDOR
B21: Anos | C21: Patrimônio Acumulado (VF) | D21: Dividendos Mensais | F21: Tipo de Fundo Imobiliário | G21: % Alocação | H21: Valor Mensal (R$)
B22: 2 | C22: =FV(taxa_mensal, B22*12, -aporte) -> 39514.733 | D22: =C22*taxa_mensal -> 316.11786 | F22: FIIs de Tijolo - Logística | G22: =VLOOKUP(perfil_selecionado & F22, 'planilha 2'!$A:$D, 4, FALSE) -> 0.25 | H22: =aporte * G22 -> 375
B23: 5 | C23: =FV(taxa_mensal, B23*12, -aporte) -> 114935.8 | D23: =C23*taxa_mensal -> 919.4864 | F23: FIIs de Tijolo - Shopping | G23: =VLOOKUP(perfil_selecionado & F23, 'planilha 2'!$A:$D, 4, FALSE) -> 0.2 | H23: =aporte * G23 -> 300
B24: 10 | C24: =FV(taxa_mensal, B24*12, -aporte) -> 300326.2 | D24: =C24*taxa_mensal -> 2402.6096 | F24: FIIs de Papel (CRI) | G24: =VLOOKUP(perfil_selecionado & F24, 'planilha 2'!$A:$D, 4, FALSE) -> 0.25 | H24: =aporte * G24 -> 375
B25: 20 | C25: =FV(taxa_mensal, B25*12, -aporte) -> 1081696.8 | D25: =C25*taxa_mensal -> 8653.5746 | F25: Fundos de Fundos (FoF) | G25: =VLOOKUP(perfil_selecionado & F25, 'planilha 2'!$A:$D, 4, FALSE) -> 0.15 | H25: =aporte * G25 -> 225
B26: 30 | C26: =FV(taxa_mensal, B26*12, -aporte) -> 3114619.8 | D26: =C26*taxa_mensal -> 24916.959 | F26: Fiagros (Agronegócio) | G26: =VLOOKUP(perfil_selecionado & F26, 'planilha 2'!$A:$D, 4, FALSE) -> 0.1 | H26: =aporte * G26 -> 150
F27: FIIs de Tijolo - Lajes Corp. | G27: =VLOOKUP(perfil_selecionado & F27, 'planilha 2'!$A:$D, 4, FALSE) -> 0.05 | H27: =aporte * G27 -> 75
F28: TOTAL | G28: =SUM(G22:G27) -> 1 | H28: =SUM(H22:H27) -> 1500

Sheet planilha 2
A1: Chave Composta | B1: Perfil | C1: Tipo de Fundo | D1: %
A2: =B2&C2 -> ConservadorFIIs de Tijolo - Logística | B2: Conservador | C2: FIIs de Tijolo - Logística | D2: 0.3
A3: =B3&C3 -> ConservadorFIIs de Tijolo - Shopping | B3: Conservador | C3: FIIs de Tijolo - Shopping | D3: 0.2
A4: =B4&C4 -> ConservadorFIIs de Papel (CRI) | B4: Conservador | C4: FIIs de Papel (CRI) | D4: 0.3
A5: =B5&C5 -> ConservadorFundos de Fundos (FoF) | B5: Conservador | C5: Fundos de Fundos (FoF) | D5: 0.1
A6: =B6&C6 -> ConservadorFiagros (Agronegócio) | B6: Conservador | C6: Fiagros (Agronegócio) | D6: 0.05
A7: =B7&C7 -> ConservadorFIIs de Tijolo - Lajes Corp. | B7: Conservador | C7: FIIs de Tijolo - Lajes Corp. | D7: 0.05
A8: =B8&C8 -> ModeradoFIIs de Tijolo - Logística | B8: Moderado | C8: FIIs de Tijolo - Logística | D8: 0.25
A9: =B9&C9 -> ModeradoFIIs de Tijolo - Shopping | B9: Moderado | C9: FIIs de Tijolo - Shopping | D9: 0.2
A10: =B10&C10 -> ModeradoFIIs de Papel (CRI) | B10: Moderado | C10: FIIs de Papel (CRI) | D10: 0.25
A11: =B11&C11 -> ModeradoFundos de Fundos (FoF) | B11: Moderado | C11: Fundos de Fundos (FoF) | D11: 0.15
A12: =B12&C12 -> ModeradoFiagros (Agronegócio) | B12: Moderado | C12: Fiagros (Agronegócio) | D12: 0.1
A13: =B13&C13 -> ModeradoFIIs de Tijolo - Lajes Corp. | B13: Moderado | C13: FIIs de Tijolo - Lajes Corp. | D13: 0.05
... A19: =B19&C19 -> ArrojadoFIIs de Tijolo - Lajes Corp. | B19: Arrojado | C19: FIIs de Tijolo - Lajes Corp. | D19: 0.15
